arkvatar/__init__.py
arkvatar/arkvatar.py
arkvatar/client.py
arkvatar-1.0.0.dist-info/LICENSE.md
arkvatar-1.0.0.dist-info/METADATA
arkvatar-1.0.0.dist-info/WHEEL
arkvatar-1.0.0.dist-info/top_level.txt
arkvatar-1.0.0.dist-info/RECORD
