Metadata-Version: 2.1
Name: arkvatar
Version: 1.0.0
Summary: API Wrapper to interact with Arkvatar.
Home-page: https://github.com/thegoldenhorde/arkvatar-py
Author: Jolan Beer - Highjhacker
Author-email: jolanbeer@gmail.com
License: UNKNOWN
Platform: UNKNOWN
Classifier: Programming Language :: Python :: 3
Classifier: License :: OSI Approved :: MIT License
Classifier: Operating System :: OS Independent
Classifier: Development Status :: 4 - Beta
Classifier: Intended Audience :: Developers
Classifier: Topic :: Software Development :: Build Tools
Requires-Python: >=3
Requires-Dist: aiohttp
